{
  "last_update": "2022-04-02T01:48:17.449Z",
  "entries": [
    {
      "word": "Abbrccn",
      "def": "“abbraccini”, ma solo se siete giovanз come Lorro 😎",
      "source": {
        "id": 49267910,
        "title": "184: Ultra Realtà",
        "link": "https://www.spreaker.com/user/10653829/184-ultra-realta"
      }
    },
    {
      "word": "Abb",
      "def": "“abbraccini”, ma solo se siete MEGA giovanз come Sio 😎👌💯",
      "source": {
        "id": 49267910,
        "title": "184: Ultra Realtà",
        "link": "https://www.spreaker.com/user/10653829/184-ultra-realta"
      }
    },
    {
      "word": "“Wababa”",
      "def": "rumore che bisogna emettere quando tornate in puntata",
      "source": {
        "id": 49016468,
        "title": "182: Evil Bull",
        "link": "https://www.spreaker.com/user/10653829/182-evil-bull"
      }
    },
    {
      "word": "Sucker",
      "def": "no, non la torta sacher -_-",
      "source": {
        "id": 49016468,
        "title": "182: Evil Bull",
        "link": "https://www.spreaker.com/user/10653829/182-evil-bull"
      }
    },
    {
      "word": "Qualità negative",
      "def": "difetti :V",
      "source": {
        "id": 48844401,
        "title": "180: Cucchiaino di Manzo",
        "link": "https://www.spreaker.com/user/10653829/180-cucchiaino-di-manzo"
      }
    },
    {
      "word": "Jihad",
      "def": "screzi tra tizi delle granite e quelli dei gelati",
      "source": {
        "id": 48844401,
        "title": "180: Cucchiaino di Manzo",
        "link": "https://www.spreaker.com/user/10653829/180-cucchiaino-di-manzo"
      }
    },
    {
      "word": "Vedere attraverso un piano",
      "def": "non essere ingannati da (da “see through something”)",
      "source": {
        "id": 48760775,
        "title": "179: Washingtown",
        "link": "https://www.spreaker.com/user/10653829/179-washingtown"
      }
    },
    {
      "word": "Rotola giù dalla lingua",
      "def": "è facile da pronunciare (da “rolls off the tongue”)",
      "source": {
        "id": 48760775,
        "title": "179: Washingtown",
        "link": "https://www.spreaker.com/user/10653829/179-washingtown"
      }
    },
    {
      "word": "Signare",
      "def": "assumere (da “to sign up”)",
      "source": {
        "id": 48572248,
        "title": "177: Olio al Sapore",
        "link": "https://www.spreaker.com/user/10653829/177-olio-al-sapore"
      }
    },
    {
      "word": "Monogorro",
      "def": "un monologo, ma solo se a farlo è Lorro",
      "source": {
        "id": 48378789,
        "title": "175: Maratona della Pizza (Pizza)",
        "link": "https://www.spreaker.com/user/10653829/175-maratona-della-pizza-pizza"
      }
    },
    {
      "word": "Grippo",
      "def": "lamentela (da “gripe”)",
      "source": {
        "id": 48280138,
        "title": "174: Topinambur Vegani",
        "link": "https://www.spreaker.com/user/10653829/174-topinambur-vegani"
      }
    },
    {
      "word": "Redimmare",
      "def": "redimere",
      "source": {
        "id": 48280138,
        "title": "174: Topinambur Vegani",
        "link": "https://www.spreaker.com/user/10653829/174-topinambur-vegani"
      }
    },
    {
      "word": "Olfo",
      "def": "satollo, molto pieno di cibo",
      "source": {
        "id": 48037355,
        "title": "172: Muffin Giganteschi",
        "link": "https://www.spreaker.com/user/10653829/172-muffin-giganteschi"
      }
    },
    {
      "word": "Infanciullezza",
      "def": "Infanzia ma meglio",
      "source": {
        "id": 47958360,
        "title": "171: Scacco Pazzo",
        "link": "https://www.spreaker.com/user/10653829/171-scacco-pazzo"
      }
    },
    {
      "word": "Colpo di sorpresa",
      "def": "come il colpo di scena, ma ancora di più",
      "source": {
        "id": 47753297,
        "title": "169: TITOLO",
        "link": "https://www.spreaker.com/user/10653829/169-titolo"
      }
    },
    {
      "word": "Dettaogli",
      "def": "dettagli, ma di Roma",
      "source": {
        "id": 47753297,
        "title": "169: TITOLO",
        "link": "https://www.spreaker.com/user/10653829/169-titolo"
      }
    },
    {
      "word": "“Cuttare un po’ di slack”",
      "def": "“non essere troppo severo con” (da: to cut some slack)",
      "source": {
        "id": 47426716,
        "title": "166: Russian Friggitelli",
        "link": "https://www.spreaker.com/user/10653829/166-russian-friggitelli"
      }
    },
    {
      "word": "Inaxpectated (??)",
      "def": "inaspettato",
      "source": {
        "id": 46974700,
        "title": "162: Miitroid",
        "link": "https://www.spreaker.com/user/10653829/162-miitroid"
      }
    },
    {
      "word": "Sbravo",
      "def": "il contrario di “bravo”",
      "source": {
        "id": 46776934,
        "title": "160: Sbravo",
        "link": "https://www.spreaker.com/user/10653829/160-sbravo"
      }
    },
    {
      "word": "Overcamare",
      "def": "superare (da “overcome”)",
      "source": {
        "id": 46776934,
        "title": "160: Sbravo",
        "link": "https://www.spreaker.com/user/10653829/160-sbravo"
      }
    },
    {
      "word": "Dialare a",
      "def": "“alzare a”",
      "source": {
        "id": 46654473,
        "title": "159: Un Bicchiere di Aspirina",
        "link": "https://www.spreaker.com/user/10653829/159-un-bicchiere-di-aspirina"
      }
    },
    {
      "word": "Attuale",
      "def": "reale/effettivo (da “actual”)",
      "source": {
        "id": 46344098,
        "title": "157: Deprovevole vs Deprivevole",
        "link": "https://www.spreaker.com/user/10653829/157-deprovevole-vs-deprivevole"
      }
    },
    {
      "word": "Inviare un proiettile da una pistola",
      "def": "sparare",
      "source": {
        "id": 46158073,
        "title": "155: There Is No Puntata (con Kenobit)",
        "link": "https://www.spreaker.com/user/10653829/155-there-is-no-puntata"
      }
    },
    {
      "word": "Ammarare",
      "def": "“ammalare” se siete delle navi",
      "source": {
        "id": 46070066,
        "title": "154: Gioielli da Mettersi Sotto la Pelle",
        "link": "https://www.spreaker.com/user/10653829/154-gioielli-da-mettersi-sotto-la-pelle"
      }
    },
    {
      "word": "Spelloutare",
      "def": "dire esplicitamente, precisare (da “to spell out”)",
      "source": {
        "id": 45440315,
        "title": "147: Zelda Acqua Secca",
        "link": "https://www.spreaker.com/user/10653829/147-zelda-acqua-secca"
      }
    },
    {
      "word": "Driftano",
      "def": "vagabondano, girovagano (esiste un termine italiano a quanto pare :V )",
      "source": {
        "id": 45343712,
        "title": "146: l'Uomuomo™",
        "link": "https://www.spreaker.com/user/10653829/146-luomuomo"
      }
    },
    {
      "word": "Tonedownare",
      "def": "smorzare, attenuare (da “tone down”)",
      "source": {
        "id": 45343712,
        "title": "146: l'Uomuomo™",
        "link": "https://www.spreaker.com/user/10653829/146-luomuomo"
      }
    },
    {
      "word": "Painstakingly",
      "def": "CON UN SACCO DI DOLORE",
      "source": {
        "id": 45162521,
        "title": "144: Un Misterioso Dentifricio",
        "link": "https://www.spreaker.com/user/10653829/144-un-misterioso-dentifricio"
      }
    },
    {
      "word": "Echo Bubble",
      "def": "come l’Echo Chamber, solo con un nome sbagliato",
      "source": {
        "id": 45054320,
        "title": "143: PPP - The Rientro pt.2",
        "link": "https://www.spreaker.com/user/10653829/143-ppp-the-rientro-pt-2"
      }
    },
    {
      "word": "Spellare",
      "def": "“fare lo spelling” (to spell)",
      "source": {
        "id": 44947342,
        "title": "142: PPP - The Rientro pt.1 (con Guarnaboy)",
        "link": "https://www.spreaker.com/user/10653829/142-ppp-the-rientro-pt-1"
      }
    },
    {
      "word": "Sgarzolo",
      "def": "fico, alla moda, che piace ai giovani",
      "source": {
        "id": 44435570,
        "title": "139: PPP Double Feature",
        "link": "https://www.spreaker.com/user/10653829/139-ppp-double-feature"
      }
    },
    {
      "word": "Assuefino",
      "def": "è giusto? non lo è? noi di certo non ne abbiamo idea :v",
      "source": {
        "id": 44435570,
        "title": "139: PPP Double Feature",
        "link": "https://www.spreaker.com/user/10653829/139-ppp-double-feature"
      }
    },
    {
      "word": "Con coscienza di causa",
      "def": "“Con cognizione di causa”",
      "source": {
        "id": 44342214,
        "title": "138: NOT Galaxy Spaghetti",
        "link": "https://www.spreaker.com/user/10653829/138-not-galaxy-spaghetti"
      }
    },
    {
      "word": "Idiosincrasia",
      "def": "la parola è corretta, ma Nick intendeva “ipocrisia”",
      "source": {
        "id": 44145647,
        "title": "136: Grasspiracy",
        "link": "https://www.spreaker.com/user/10653829/136-grasspiracy"
      }
    },
    {
      "word": "Ditobait",
      "def": "clickbait, ma del futuro (presente)",
      "source": {
        "id": 44145647,
        "title": "136: Grasspiracy",
        "link": "https://www.spreaker.com/user/10653829/136-grasspiracy"
      }
    },
    {
      "word": "Finanzi",
      "def": "operazioni finanziarie (tipo home-banking)",
      "source": {
        "id": 44049734,
        "title": "135: Il Comic Sans è Bidoof",
        "link": "https://www.spreaker.com/user/10653829/135-il-comic-sans-e-bidoof"
      }
    },
    {
      "word": "Flesh-outare",
      "def": "“sviluppare” (to flesh out)",
      "source": {
        "id": 44049734,
        "title": "135: Il Comic Sans è Bidoof",
        "link": "https://www.spreaker.com/user/10653829/135-il-comic-sans-e-bidoof"
      }
    },
    {
      "word": "Fitti",
      "def": "fatti, ma fittizi",
      "source": {
        "id": 44049734,
        "title": "135: Il Comic Sans è Bidoof",
        "link": "https://www.spreaker.com/user/10653829/135-il-comic-sans-e-bidoof"
      }
    },
    {
      "word": "Gnucco",
      "def": "testardo nel non fare le cose (???)",
      "source": {
        "id": 43945078,
        "title": "134: Il Protagonista di Ninja Gaiden",
        "link": "https://www.spreaker.com/user/10653829/134-il-protagonista-di-ninja-gaiden"
      }
    },
    {
      "word": "Focusare",
      "def": "concentrarsi su (da “to focus”)",
      "source": {
        "id": 43844368,
        "title": "133: Pizza of Fire - The Beginning",
        "link": "https://www.spreaker.com/user/10653829/133-pizza-of-fire-the-beginning"
      }
    },
    {
      "word": "Despaisare",
      "def": "disprezzare qlcs (da “to despise”)",
      "source": {
        "id": 43844368,
        "title": "133: Pizza of Fire - The Beginning",
        "link": "https://www.spreaker.com/user/10653829/133-pizza-of-fire-the-beginning"
      }
    },
    {
      "word": "Spararsi",
      "def": "risparmiarsi qualcosa (da “to spare”)",
      "source": {
        "id": 43587574,
        "title": "131: Mi Sono Appena Reso Conto Che Quando Dite Titolo È Veramente Il Titolo",
        "link": "https://www.spreaker.com/user/10653829/131-mi-sono-reso-conto-che-quando-dite-t"
      }
    },
    {
      "word": "S Availabile",
      "def": "disponibile",
      "source": {
        "id": 43528640,
        "title": "130: Potere e Pizza",
        "link": "https://www.spreaker.com/user/10653829/130-potere-e-pizza"
      }
    },
    {
      "word": "N Disacculturare",
      "def": "rendere meno colto; rovinare culturalmente",
      "source": {
        "id": 43528640,
        "title": "130: Potere e Pizza",
        "link": "https://www.spreaker.com/user/10653829/130-potere-e-pizza"
      }
    },
    {
      "word": "“Inezia nel fare”",
      "def": "scarsa capacità nel fare qualcosa",
      "source": {
        "id": 43161508,
        "title": "127: Molti Multilupi",
        "link": "https://www.spreaker.com/user/10653829/21-01-20-pizza-127"
      }
    },
    {
      "word": "Strizzare l’occhiolino",
      "def": "strizzare l’occhio/fare l’occhiolino",
      "source": {
        "id": 42934898,
        "title": "125: Verità - The Musical",
        "link": "https://www.spreaker.com/user/10653829/125-verita-the-musical"
      }
    },
    {
      "word": "“Rilegarci a doppia mandata”",
      "def": "relegarci",
      "source": {
        "id": 42734339,
        "title": "124: BUON ANNONE DI PPP!!",
        "link": "https://www.spreaker.com/user/10653829/124-buon-annone-di-ppp"
      }
    },
    {
      "word": "Pane croccariello",
      "def": "pane friabile, croccante",
      "source": {
        "id": 42556297,
        "title": "122: CyberBaguette 2021",
        "link": "https://www.spreaker.com/user/10653829/122-cyberbaguette-2021"
      }
    },
    {
      "word": "Embracciare",
      "def": "to embrace / abbracciare (in senso figurato)",
      "source": {
        "id": 42184693,
        "title": "119: Sedersi Come i Russi",
        "link": "https://www.spreaker.com/user/10653829/119-sedersi-come-i-russi"
      }
    },
    {
      "word": "Trovarsi in un cetriolo",
      "def": "to be in a pickle / essere “nei pasticci”",
      "source": {
        "id": 42061772,
        "title": "118: Cervelli Ricoperti di Lingua",
        "link": "https://www.spreaker.com/user/10653829/118-cervelli-ricoperti-di-lingua"
      }
    },
    {
      "word": "to powerpiz",
      "def": "voce del verbo “ascoltare Power Pizza”",
      "source": {
        "id": 41700650,
        "title": "115: Tubolare di Gusto",
        "link": "https://www.spreaker.com/user/10653829/115-tubolare-di-gusto"
      }
    },
    {
      "word": "Qualcosa che “può farvi bagnare alcuni degli occhi che avete”",
      "def": "Qualcosa che fa piangere",
      "source": {
        "id": 41700650,
        "title": "115: Tubolare di Gusto",
        "link": "https://www.spreaker.com/user/10653829/115-tubolare-di-gusto"
      }
    },
    {
      "word": "Chiamo già cacca di bue",
      "def": "“I call bullshit”",
      "source": {
        "id": 41602731,
        "title": "114: Power Pizza React to...",
        "link": "https://www.spreaker.com/user/10653829/114-power-pizza-react-to"
      }
    },
    {
      "word": "Dismissare",
      "def": "to dismiss",
      "source": {
        "id": 41602731,
        "title": "114: Power Pizza React to...",
        "link": "https://www.spreaker.com/user/10653829/114-power-pizza-react-to"
      }
    },
    {
      "word": "Shinare una spotlait",
      "def": "Portare l'attenzione su qualcosa",
      "source": {
        "id": 41494913,
        "title": "113: Power Pinsa",
        "link": "https://www.spreaker.com/user/10653829/113-power-pinsa"
      }
    },
    {
      "word": "Snowballare",
      "def": "precipitare (da snowball)",
      "source": {
        "id": 40952571,
        "title": "109: Kirby è Magalli",
        "link": "https://www.spreaker.com/user/10653829/109-kirby-e-magalli"
      }
    },
    {
      "word": "Depictionare",
      "def": "descrivere (da depict)",
      "source": {
        "id": 40679993,
        "title": "107: Menews - The Movie",
        "link": "https://www.spreaker.com/user/10653829/107-menews-the-movie"
      }
    },
    {
      "word": "Apatetico",
      "def": "apatico (da apathetic)",
      "source": {
        "id": 40679993,
        "title": "107: Menews - The Movie",
        "link": "https://www.spreaker.com/user/10653829/107-menews-the-movie"
      }
    },
    {
      "word": "Enpàssant",
      "def": "Di sfuggita, accidentalmente",
      "source": {
        "id": 40532045,
        "title": "106: Il Ritorno del Moderatore",
        "link": "https://www.spreaker.com/user/10653829/106-il-ritorno-del-moderatore"
      }
    },
    {
      "word": "Greidato",
      "def": "Graded (da color grading)",
      "source": {
        "id": 40532045,
        "title": "106: Il Ritorno del Moderatore",
        "link": "https://www.spreaker.com/user/10653829/106-il-ritorno-del-moderatore"
      }
    },
    {
      "word": "Docked",
      "def": "Guerre Stellari",
      "source": {
        "id": 40405763,
        "title": "105: Star Star",
        "link": "https://www.spreaker.com/user/10653829/105-star-star"
      }
    },
    {
      "word": "Gullibile",
      "def": "Credulone",
      "source": {
        "id": 40405763,
        "title": "105: Star Star",
        "link": "https://www.spreaker.com/user/10653829/105-star-star"
      }
    },
    {
      "word": "Spinzettarsi",
      "def": "Farsi i peli con estrema foga/trasporto",
      "source": {
        "id": 40405763,
        "title": "105: Star Star",
        "link": "https://www.spreaker.com/user/10653829/105-star-star"
      }
    },
    {
      "word": "Ledges delle piattaforme",
      "def": "I bordi delle piattaforme",
      "source": {
        "id": 40405763,
        "title": "105: Star Star",
        "link": "https://www.spreaker.com/user/10653829/105-star-star"
      }
    },
    {
      "word": "Naf Sed",
      "def": "Aver già detto abbastanza",
      "source": {
        "id": 40317480,
        "title": "104: Non Dire Niente",
        "link": "https://www.spreaker.com/user/10653829/104-non-dire-niente"
      }
    },
    {
      "word": "Titillare l’anima",
      "def": "Rendere felici internamente",
      "source": {
        "id": 40187033,
        "title": "103: Conditio Sine Qui Quo Qua Non",
        "link": "https://www.spreaker.com/user/10653829/103-conditio-sine-qui-quo-qua-non"
      }
    },
    {
      "word": "Conditio Sine Qua Non",
      "def": "Megaprerequisito importante",
      "source": {
        "id": 40187033,
        "title": "103: Conditio Sine Qui Quo Qua Non",
        "link": "https://www.spreaker.com/user/10653829/103-conditio-sine-qui-quo-qua-non"
      }
    },
    {
      "word": "Zebedei",
      "def": "Testicoli",
      "source": {
        "id": 40187033,
        "title": "103: Conditio Sine Qui Quo Qua Non",
        "link": "https://www.spreaker.com/user/10653829/103-conditio-sine-qui-quo-qua-non"
      }
    },
    {
      "word": "Lettore di vinili",
      "def": "Giradischi",
      "source": {
        "id": 40187033,
        "title": "103: Conditio Sine Qui Quo Qua Non",
        "link": "https://www.spreaker.com/user/10653829/103-conditio-sine-qui-quo-qua-non"
      }
    },
    {
      "word": "Iperlativo",
      "def": "super superlativo",
      "source": {
        "id": 40051942,
        "title": "102: What He Does in the Mirror",
        "link": "https://www.spreaker.com/user/10653829/102-what-he-does-in-the-mirror"
      }
    },
    {
      "word": "Gigglare",
      "def": "to giggle",
      "source": {
        "id": 40051942,
        "title": "102: What He Does in the Mirror",
        "link": "https://www.spreaker.com/user/10653829/102-what-he-does-in-the-mirror"
      }
    },
    {
      "word": "Essere in un sottaceto",
      "def": "Being in a pickle",
      "source": {
        "id": 39931142,
        "title": "101: Forsureadowing",
        "link": "https://www.spreaker.com/user/10653829/101-forsureadowing"
      }
    },
    {
      "word": "Buco di coniglio",
      "def": "Rabbit Hole",
      "source": {
        "id": 39931142,
        "title": "101: Forsureadowing",
        "link": "https://www.spreaker.com/user/10653829/101-forsureadowing"
      }
    },
    {
      "word": "Gibberiscia",
      "def": "gibberish🦆",
      "source": {
        "id": 39793410,
        "title": "100: Cento Fette di Pizza",
        "link": "https://www.spreaker.com/user/10653829/100-cento-fette-di-pizza"
      }
    },
    {
      "word": "Arrakis",
      "def": "formula magica segreta che fa ridere Nik😅😅😅😅😅😭😞💪😄🦾🐡💥",
      "source": {
        "id": 39793410,
        "title": "100: Cento Fette di Pizza",
        "link": "https://www.spreaker.com/user/10653829/100-cento-fette-di-pizza"
      }
    },
    {
      "word": "Timely",
      "def": "temposo➡️➡️➡️▪️▪️▪️▪️😱👈🎶🎶🎶👇😱",
      "source": {
        "id": 39793410,
        "title": "100: Cento Fette di Pizza",
        "link": "https://www.spreaker.com/user/10653829/100-cento-fette-di-pizza"
      }
    },
    {
      "word": "Ignifugicità",
      "def": "Essere ignifugico🔥🧯🔥🔥🔥🔥🧯🧯😱",
      "source": {
        "id": 39793410,
        "title": "100: Cento Fette di Pizza",
        "link": "https://www.spreaker.com/user/10653829/100-cento-fette-di-pizza"
      }
    },
    {
      "word": "Ingioiare",
      "def": "rendere gioio😘😘😘😘🎶🎶🇺🇸",
      "source": {
        "id": 39793410,
        "title": "100: Cento Fette di Pizza",
        "link": "https://www.spreaker.com/user/10653829/100-cento-fette-di-pizza"
      }
    },
    {
      "word": "Workare",
      "def": "Fare funzionare qualcosa in un dato contesto",
      "source": {
        "id": 33225239,
        "title": "ep.97: L'Italiano Appena",
        "link": "https://www.spreaker.com/user/10653829/ep-97-litaliano-appena"
      }
    },
    {
      "word": "Mockare",
      "def": "Farsi beffe di",
      "source": {
        "id": 31665151,
        "title": "ep.96: Alla Faccia Tua, Fabio",
        "link": "https://www.spreaker.com/user/10653829/ep-96-alla-faccia-tua-fabio"
      }
    },
    {
      "word": "Nicktus",
      "def": "Ictus che ti causa il non sapere le frasi",
      "source": {
        "id": 30269291,
        "title": "ep.95: Il Latino è Delizioso",
        "link": "https://www.spreaker.com/user/10653829/ep-95-il-latino-e-delizioso"
      }
    },
    {
      "word": "Overvendere",
      "def": "NO DAVVERO BELLISSIMO NON AVETE IDEA",
      "source": {
        "id": 29272877,
        "title": "ep.94: Non Fidatevi di Noi",
        "link": "https://www.spreaker.com/user/10653829/ep-94-non-fidatevi-di-noi"
      }
    },
    {
      "word": "Mediolina",
      "def": "Non ottimina, non bassina. Mediolina.",
      "source": {
        "id": 29272877,
        "title": "ep.94: Non Fidatevi di Noi",
        "link": "https://www.spreaker.com/user/10653829/ep-94-non-fidatevi-di-noi"
      }
    },
    {
      "word": "Pannelli",
      "def": "Conferenze",
      "source": {
        "id": 28014851,
        "title": "ep.92: Mi Sentivo una Persona Piena di Nozioni",
        "link": "https://www.spreaker.com/user/10653829/ep-92-mi-sentivo-una-persona-piena-di-no"
      }
    },
    {
      "word": "Cacaio",
      "def": "Casino assurdo fratm",
      "source": {
        "id": 27325443,
        "title": "ep.91: Fin Sopra le Tasche",
        "link": "https://www.spreaker.com/user/10653829/ep-91-fin-sopra-le-tasche"
      }
    },
    {
      "word": "Permeanza",
      "def": "Presenza (??) - andate a chiederlo a Nick",
      "source": {
        "id": 27325443,
        "title": "ep.91: Fin Sopra le Tasche",
        "link": "https://www.spreaker.com/user/10653829/ep-91-fin-sopra-le-tasche"
      }
    },
    {
      "word": "Gullibile",
      "def": "Credulone",
      "source": {
        "id": 26873138,
        "title": "ep.90: For All Cows",
        "link": "https://www.spreaker.com/user/10653829/ep-90-for-all-cows"
      }
    },
    {
      "word": "Diramare",
      "def": "????????????",
      "source": {
        "id": 26417549,
        "title": "ep.89: Turbo, Metallo & Brugola",
        "link": "https://www.spreaker.com/user/10653829/20-04-21-pizza-89"
      }
    },
    {
      "word": "Piuttosto che",
      "def": "Oppure (non usatelo così per piacere)",
      "source": {
        "id": 26417549,
        "title": "ep.89: Turbo, Metallo & Brugola",
        "link": "https://www.spreaker.com/user/10653829/20-04-21-pizza-89"
      }
    },
    {
      "word": "Taika Waititi",
      "def": "L’amichetto migliore di Nik",
      "source": {
        "id": 26417549,
        "title": "ep.89: Turbo, Metallo & Brugola",
        "link": "https://www.spreaker.com/user/10653829/20-04-21-pizza-89"
      }
    },
    {
      "word": "Puntare l’attenzione",
      "def": "Portare alla vostra attenzione",
      "source": {
        "id": 26417549,
        "title": "ep.89: Turbo, Metallo & Brugola",
        "link": "https://www.spreaker.com/user/10653829/20-04-21-pizza-89"
      }
    },
    {
      "word": "Oro Colato dal Cielo",
      "def": "Contro ogni aspettativa, una cosa bella",
      "source": {
        "id": 25949350,
        "title": "ep.88: The Brilliant Denti Nuovi",
        "link": "https://www.spreaker.com/user/10653829/ep-88-the-brilliant-denti-nuovi"
      }
    },
    {
      "word": "Deliverare le battute",
      "def": "Recitare le proprie battute",
      "source": {
        "id": 25606311,
        "title": "ep.87: Dottor Lamentino",
        "link": "https://www.spreaker.com/user/10653829/ep-87-dottor-lamentino"
      }
    },
    {
      "word": "Viabile",
      "def": "Praticabile, attuabile, (da Viable)",
      "source": {
        "id": 25139201,
        "title": "ep.86: Bacon as Anything",
        "link": "https://www.spreaker.com/user/10653829/ep-86-bacon-as-anything"
      }
    },
    {
      "word": "Postclaimer",
      "def": "Disclaimer, ma dopo, quindi non serve a niente",
      "source": {
        "id": 25139201,
        "title": "ep.86: Bacon as Anything",
        "link": "https://www.spreaker.com/user/10653829/ep-86-bacon-as-anything"
      }
    },
    {
      "word": "Enforzare",
      "def": "Far rispettare",
      "source": {
        "id": 24746114,
        "title": "ep.85: Pizza con la Frutta",
        "link": "https://www.spreaker.com/user/10653829/ep-85-pizza-con-la-frutta"
      }
    },
    {
      "word": "Un centottanta",
      "def": "Mezzo trecentosessanta",
      "source": {
        "id": 24746114,
        "title": "ep.85: Pizza con la Frutta",
        "link": "https://www.spreaker.com/user/10653829/ep-85-pizza-con-la-frutta"
      }
    },
    {
      "word": "ENGIAIN",
      "def": "Engine, “motore grafico”",
      "source": {
        "id": 24056091,
        "title": "ep.83: Attendere Vigorosamente VII",
        "link": "https://www.spreaker.com/user/10653829/ep-83-attendere-vigorosamente-vii"
      }
    },
    {
      "word": "Fair Enough",
      "def": "Severo ma giusto",
      "source": {
        "id": 24056091,
        "title": "ep.83: Attendere Vigorosamente VII",
        "link": "https://www.spreaker.com/user/10653829/ep-83-attendere-vigorosamente-vii"
      }
    },
    {
      "word": "Lorro",
      "def": "Non Nik",
      "source": {
        "id": 24056091,
        "title": "ep.83: Attendere Vigorosamente VII",
        "link": "https://www.spreaker.com/user/10653829/ep-83-attendere-vigorosamente-vii"
      }
    },
    {
      "word": "Corroborare",
      "def": "Wow Nik ha usato questa parola correttamente",
      "source": {
        "id": 24056091,
        "title": "ep.83: Attendere Vigorosamente VII",
        "link": "https://www.spreaker.com/user/10653829/ep-83-attendere-vigorosamente-vii"
      }
    },
    {
      "word": "Angolodown",
      "def": "Topdown, ma un po’ sfasato",
      "source": {
        "id": 24056091,
        "title": "ep.83: Attendere Vigorosamente VII",
        "link": "https://www.spreaker.com/user/10653829/ep-83-attendere-vigorosamente-vii"
      }
    },
    {
      "word": "Confidenza",
      "def": "Confidence",
      "source": {
        "id": 23793376,
        "title": "ep.82: Gommoso e Stantio",
        "link": "https://www.spreaker.com/user/10653829/ep-82-gommoso-e-stantio"
      }
    },
    {
      "word": "Saccate",
      "def": "grandi quantità",
      "source": {
        "id": 23793376,
        "title": "ep.82: Gommoso e Stantio",
        "link": "https://www.spreaker.com/user/10653829/ep-82-gommoso-e-stantio"
      }
    },
    {
      "word": "Blu",
      "def": "Colore della velocità",
      "source": {
        "id": 23793376,
        "title": "ep.82: Gommoso e Stantio",
        "link": "https://www.spreaker.com/user/10653829/ep-82-gommoso-e-stantio"
      }
    },
    {
      "word": "Networcone",
      "def": "Network, ma più grosso",
      "source": {
        "id": 23793376,
        "title": "ep.82: Gommoso e Stantio",
        "link": "https://www.spreaker.com/user/10653829/ep-82-gommoso-e-stantio"
      }
    },
    {
      "word": "Triggerare",
      "def": "Lavorare per lo studio Trigger",
      "source": {
        "id": 23793376,
        "title": "ep.82: Gommoso e Stantio",
        "link": "https://www.spreaker.com/user/10653829/ep-82-gommoso-e-stantio"
      }
    },
    {
      "word": "Rooster",
      "def": "Roster",
      "source": {
        "id": 23793376,
        "title": "ep.82: Gommoso e Stantio",
        "link": "https://www.spreaker.com/user/10653829/ep-82-gommoso-e-stantio"
      }
    },
    {
      "word": "Unanimamente",
      "def": "Unanimemente",
      "source": {
        "id": 23793376,
        "title": "ep.82: Gommoso e Stantio",
        "link": "https://www.spreaker.com/user/10653829/ep-82-gommoso-e-stantio"
      }
    },
    {
      "word": "Antitaschi",
      "def": "????",
      "source": {
        "id": 23793376,
        "title": "ep.82: Gommoso e Stantio",
        "link": "https://www.spreaker.com/user/10653829/ep-82-gommoso-e-stantio"
      }
    },
    {
      "word": "Teatro",
      "def": "Cinema dei professoroni",
      "source": {
        "id": 23538913,
        "title": "ep.81: Cos'è il Cinque?",
        "link": "https://www.spreaker.com/user/10653829/ep-81-cose-il-cinque"
      }
    },
    {
      "word": "Pizzillanime",
      "def": "Pusillanime amante dei caroboidrati",
      "source": {
        "id": 23538913,
        "title": "ep.81: Cos'è il Cinque?",
        "link": "https://www.spreaker.com/user/10653829/ep-81-cose-il-cinque"
      }
    },
    {
      "word": "Smoderato",
      "def": "Smodato",
      "source": {
        "id": 23538913,
        "title": "ep.81: Cos'è il Cinque?",
        "link": "https://www.spreaker.com/user/10653829/ep-81-cose-il-cinque"
      }
    },
    {
      "word": "Scor",
      "def": "La colonna sonora",
      "source": {
        "id": 23257164,
        "title": "ep.80: Re Miles",
        "link": "https://www.spreaker.com/user/10653829/ep-80-re-miles"
      }
    },
    {
      "word": "Nomenclare",
      "def": "Non esiste questo verbo dannazione Nik",
      "source": {
        "id": 23059501,
        "title": "ep.79: Io non mi faccio domande, mi do solo risposte.",
        "link": "https://www.spreaker.com/user/10653829/ep-79-io-non-mi-faccio-domande-mi-do-sol"
      }
    },
    {
      "word": "TRU FACTS OF THE SINEMA",
      "def": "Trivia generici",
      "source": {
        "id": 23059501,
        "title": "ep.79: Io non mi faccio domande, mi do solo risposte.",
        "link": "https://www.spreaker.com/user/10653829/ep-79-io-non-mi-faccio-domande-mi-do-sol"
      }
    },
    {
      "word": "ANSAMBZL",
      "def": "Ensemble",
      "source": {
        "id": 23059501,
        "title": "ep.79: Io non mi faccio domande, mi do solo risposte.",
        "link": "https://www.spreaker.com/user/10653829/ep-79-io-non-mi-faccio-domande-mi-do-sol"
      }
    },
    {
      "word": "Cazzimma sufficiente",
      "def": "cazzimma appropriatamente adeguata",
      "source": {
        "id": 22731245,
        "title": "ep.78: The Bizarre World of Picard",
        "link": "https://www.spreaker.com/user/10653829/ep-78-the-bizarre-world-of-picard"
      }
    },
    {
      "word": "In medias res",
      "def": "assolutamente non quello che vuol dire in medias res",
      "source": {
        "id": 22731245,
        "title": "ep.78: The Bizarre World of Picard",
        "link": "https://www.spreaker.com/user/10653829/ep-78-the-bizarre-world-of-picard"
      }
    },
    {
      "word": "Dismembrato",
      "def": "“smembrato”, ma detto da un analfabeta",
      "source": {
        "id": 22198876,
        "title": "ep.76: The Blair Witcher Project",
        "link": "https://www.spreaker.com/user/10653829/ep-76-the-blair-witcher-project"
      }
    },
    {
      "word": "Overcommittare",
      "def": "impegnarsi davvero molto in qualcosa che guarda, che impegno",
      "source": {
        "id": 22198876,
        "title": "ep.76: The Blair Witcher Project",
        "link": "https://www.spreaker.com/user/10653829/ep-76-the-blair-witcher-project"
      }
    },
    {
      "word": "WOOOOW",
      "def": "wow",
      "source": {
        "id": 22198876,
        "title": "ep.76: The Blair Witcher Project",
        "link": "https://www.spreaker.com/user/10653829/ep-76-the-blair-witcher-project"
      }
    },
    {
      "word": "Macrabah",
      "def": "leggendaria città di Macradin",
      "source": {
        "id": 22198876,
        "title": "ep.76: The Blair Witcher Project",
        "link": "https://www.spreaker.com/user/10653829/ep-76-the-blair-witcher-project"
      }
    },
    {
      "word": "Outtare",
      "def": "Rivelare l’identità di una persona terza",
      "source": {
        "id": 21778860,
        "title": "ep.75: Space Klaus",
        "link": "https://www.spreaker.com/user/10653829/ep-75-space-klaus"
      }
    },
    {
      "word": "Tute dell’ossigeno",
      "def": "Tute spaziali",
      "source": {
        "id": 21778860,
        "title": "ep.75: Space Klaus",
        "link": "https://www.spreaker.com/user/10653829/ep-75-space-klaus"
      }
    },
    {
      "word": "Mascherine particolari",
      "def": "Mascherine molto speciali",
      "source": {
        "id": 21778860,
        "title": "ep.75: Space Klaus",
        "link": "https://www.spreaker.com/user/10653829/ep-75-space-klaus"
      }
    },
    {
      "word": "Plutone",
      "def": "Nettuno",
      "source": {
        "id": 21778860,
        "title": "ep.75: Space Klaus",
        "link": "https://www.spreaker.com/user/10653829/ep-75-space-klaus"
      }
    },
    {
      "word": "Scellerati",
      "def": "Super Folli",
      "source": {
        "id": 21778860,
        "title": "ep.75: Space Klaus",
        "link": "https://www.spreaker.com/user/10653829/ep-75-space-klaus"
      }
    },
    {
      "word": "PERENTURO",
      "def": "Perenne e duraturo (o peperone e avventuro)",
      "source": {
        "id": 21539479,
        "title": "ep.74: JoJo Pizza",
        "link": "https://www.spreaker.com/user/10653829/ep-74-jojo-pizza"
      }
    },
    {
      "word": "SMONARE",
      "def": "Rattristare",
      "source": {
        "id": 21539479,
        "title": "ep.74: JoJo Pizza",
        "link": "https://www.spreaker.com/user/10653829/ep-74-jojo-pizza"
      }
    },
    {
      "word": "ENDORSARE",
      "def": "Fare un endorsement,",
      "source": {
        "id": 21539479,
        "title": "ep.74: JoJo Pizza",
        "link": "https://www.spreaker.com/user/10653829/ep-74-jojo-pizza"
      }
    },
    {
      "word": "GUERRE STELLARI",
      "def": "Star Wars",
      "source": {
        "id": 21539479,
        "title": "ep.74: JoJo Pizza",
        "link": "https://www.spreaker.com/user/10653829/ep-74-jojo-pizza"
      }
    },
    {
      "word": "Carboigrizia",
      "def": "Pigrizia da carboidrati",
      "source": {
        "id": 21078679,
        "title": "ep.73: Cybertruck Future 88",
        "link": "https://www.spreaker.com/user/10653829/ep-73-cybertruck-future-88"
      }
    },
    {
      "word": "Rampe anti-accesso",
      "def": "???",
      "source": {
        "id": 21078679,
        "title": "ep.73: Cybertruck Future 88",
        "link": "https://www.spreaker.com/user/10653829/ep-73-cybertruck-future-88"
      }
    },
    {
      "word": "Cazzimma Americana",
      "def": "Una roba che guarda non te la spiego neanche fratm",
      "source": {
        "id": 21078679,
        "title": "ep.73: Cybertruck Future 88",
        "link": "https://www.spreaker.com/user/10653829/ep-73-cybertruck-future-88"
      }
    },
    {
      "word": "Pioniere/Curioso",
      "def": "Idiota",
      "source": {
        "id": 20678805,
        "title": "ep.71: Il Muccomplotto",
        "link": "https://www.spreaker.com/user/10653829/ep-71-il-muccomplotto"
      }
    },
    {
      "word": "FACDAP",
      "def": "Un po' cattivelli",
      "source": {
        "id": 20329676,
        "title": "ep.69: The MandorLorro",
        "link": "https://www.spreaker.com/user/10653829/ep-69-the-mandorlorro"
      }
    },
    {
      "word": "Astanti",
      "def": "Che stanno intorno",
      "source": {
        "id": 20329676,
        "title": "ep.69: The MandorLorro",
        "link": "https://www.spreaker.com/user/10653829/ep-69-the-mandorlorro"
      }
    },
    {
      "word": "Patent Pending",
      "def": "Ne posseggo i diritti sul copyright",
      "source": {
        "id": 20329676,
        "title": "ep.69: The MandorLorro",
        "link": "https://www.spreaker.com/user/10653829/ep-69-the-mandorlorro"
      }
    },
    {
      "word": "Blasfromthepas",
      "def": "[Blast from the past]",
      "source": {
        "id": 19776938,
        "title": "ep.66: Anarchy In The PPP",
        "link": "https://www.spreaker.com/user/10653829/ep-66-anarchy-in-the-ppp"
      }
    },
    {
      "word": "BERNARDI-INVERECONDITO",
      "def": "Dizionario in uso nelle migliori scuole di dislessia",
      "source": {
        "id": 19776938,
        "title": "ep.66: Anarchy In The PPP",
        "link": "https://www.spreaker.com/user/10653829/ep-66-anarchy-in-the-ppp"
      }
    },
    {
      "word": "BEEYOPIC",
      "def": "Biopic",
      "source": {
        "id": 19670986,
        "title": "ep.65: la Redenzione della Fanfiction",
        "link": "https://www.spreaker.com/user/10653829/ep-65-la-redenzione-della-fanfiction"
      }
    },
    {
      "word": "Caìgo",
      "def": "nebbiolona",
      "source": {
        "id": 19670986,
        "title": "ep.65: la Redenzione della Fanfiction",
        "link": "https://www.spreaker.com/user/10653829/ep-65-la-redenzione-della-fanfiction"
      }
    },
    {
      "word": "\"3d 3d che non fa finta di non essere 3d\"",
      "def": "3D tipo, metti, Shrek",
      "source": {
        "id": 19670986,
        "title": "ep.65: la Redenzione della Fanfiction",
        "link": "https://www.spreaker.com/user/10653829/ep-65-la-redenzione-della-fanfiction"
      }
    },
    {
      "word": "Spezzettoni",
      "def": "Spezzatino di argomenti, gusto brasato",
      "source": {
        "id": 19670986,
        "title": "ep.65: la Redenzione della Fanfiction",
        "link": "https://www.spreaker.com/user/10653829/ep-65-la-redenzione-della-fanfiction"
      }
    },
    {
      "word": "Opening Statement",
      "def": "Dichiarazione d’apertura",
      "source": {
        "id": 19549430,
        "title": "ep.64: LIVING IN A PIZZA SOCIETY",
        "link": "https://www.spreaker.com/user/10653829/ep-64-living-in-a-pizza-society"
      }
    },
    {
      "word": "Hablatore",
      "def": "Persona che parla",
      "source": {
        "id": 19453537,
        "title": "ep.63 : Ho le orecchie piene di Lorro",
        "link": "https://www.spreaker.com/user/10653829/ep-63-final"
      }
    },
    {
      "word": "Pinball",
      "def": "Flipper",
      "source": {
        "id": 19453537,
        "title": "ep.63 : Ho le orecchie piene di Lorro",
        "link": "https://www.spreaker.com/user/10653829/ep-63-final"
      }
    },
    {
      "word": "Trackarti",
      "def": "Seguire nello spazio",
      "source": {
        "id": 19453537,
        "title": "ep.63 : Ho le orecchie piene di Lorro",
        "link": "https://www.spreaker.com/user/10653829/ep-63-final"
      }
    },
    {
      "word": "Assolutamente sì",
      "def": "sì",
      "source": {
        "id": 19361958,
        "title": "ep.62: Tripla esplosione atomica",
        "link": "https://www.spreaker.com/user/10653829/ep-62-editato"
      }
    },
    {
      "word": "Pointa e clicca",
      "def": "punta e clicca",
      "source": {
        "id": 19361958,
        "title": "ep.62: Tripla esplosione atomica",
        "link": "https://www.spreaker.com/user/10653829/ep-62-editato"
      }
    },
    {
      "word": "Eicbiò",
      "def": "HBO",
      "source": {
        "id": 19361958,
        "title": "ep.62: Tripla esplosione atomica",
        "link": "https://www.spreaker.com/user/10653829/ep-62-editato"
      }
    },
    {
      "word": "Detachd",
      "def": "Distaccato [dall’inglese “detached”]",
      "source": {
        "id": 19177638,
        "title": "ep.60: Assassini Cereali",
        "link": "https://www.spreaker.com/user/10653829/ep-60-assassini-cereali"
      }
    },
    {
      "word": "Guilty piacere",
      "def": "Pleasure proibito",
      "source": {
        "id": 19177638,
        "title": "ep.60: Assassini Cereali",
        "link": "https://www.spreaker.com/user/10653829/ep-60-assassini-cereali"
      }
    },
    {
      "word": "Stunnare",
      "def": "Stordire [dall’inglese “stun”]",
      "source": {
        "id": 19177638,
        "title": "ep.60: Assassini Cereali",
        "link": "https://www.spreaker.com/user/10653829/ep-60-assassini-cereali"
      }
    },
    {
      "word": "Confidenza",
      "def": "Fiducia in seé stessi [dall’inglese “confidence”]",
      "source": {
        "id": 19177638,
        "title": "ep.60: Assassini Cereali",
        "link": "https://www.spreaker.com/user/10653829/ep-60-assassini-cereali"
      }
    },
    {
      "word": "Pettare",
      "def": "Fare “pat pat” sulla testa di un gatto o cane o pollo [dall’inglese “to pet”]",
      "source": {
        "id": 19177638,
        "title": "ep.60: Assassini Cereali",
        "link": "https://www.spreaker.com/user/10653829/ep-60-assassini-cereali"
      }
    },
    {
      "word": "Ecsaited",
      "def": "W o w [dall’inglese “W  O  W”]",
      "source": {
        "id": 19177638,
        "title": "ep.60: Assassini Cereali",
        "link": "https://www.spreaker.com/user/10653829/ep-60-assassini-cereali"
      }
    },
    {
      "word": "Catzin",
      "def": "Cutscene",
      "source": {
        "id": 19177638,
        "title": "ep.60: Assassini Cereali",
        "link": "https://www.spreaker.com/user/10653829/ep-60-assassini-cereali"
      }
    }
  ]
}